aioairctrl/__init__.py
aioairctrl/__main__.py
aioairctrl/cli.py
aioairctrl/coap/__init__.py
aioairctrl/coap/aiocoap_monkeypatch.py
aioairctrl/coap/client.py
aioairctrl/coap/encryption.py
aioairctrl-0.2.5.dist-info/LICENSE
aioairctrl-0.2.5.dist-info/METADATA
aioairctrl-0.2.5.dist-info/WHEEL
aioairctrl-0.2.5.dist-info/entry_points.txt
aioairctrl-0.2.5.dist-info/top_level.txt
aioairctrl-0.2.5.dist-info/RECORD
