Metadata-Version: 2.1
Name: aioairctrl
Version: 0.2.5
Summary: Library for controlling Philips air purifiers (using encrypted CoAP)
Home-page: https://github.com/kongo09/aioairctrl
Author: betaboon
License: MIT
Project-URL: Bug Tracker, https://github.com/kongo09/aioairctrl/issues
Requires-Python: >=3.6
License-File: LICENSE
Requires-Dist: pycryptodomex
Requires-Dist: aiocoap<0.5,>=0.4.7
